{"format":2,"version":"5.3","globals":"7165ae86dce56b0334d849dcc4b58b51","files":{"tarjinja___init___py":{"hash":"fa6d7da91583d1b586bf1e7ac870ecb0","index":{"nums":[1,15,0,0,0,0,0],"html_filename":"tarjinja___init___py.html","relative_filename":"tarjinja/__init__.py"}},"tarjinja_choice_py":{"hash":"eddae9b812d3e438b0d9dea42f1c33a1","index":{"nums":[1,56,0,13,0,0,0],"html_filename":"tarjinja_choice_py.html","relative_filename":"tarjinja/choice.py"}},"tarjinja_dictio_py":{"hash":"04eb4fcba0440c3669ec48fa02f06e5e","index":{"nums":[1,20,0,0,0,0,0],"html_filename":"tarjinja_dictio_py.html","relative_filename":"tarjinja/dictio.py"}},"tarjinja_dirtree_py":{"hash":"0e63cedd832465f29265b63065c63562","index":{"nums":[1,50,0,2,0,0,0],"html_filename":"tarjinja_dirtree_py.html","relative_filename":"tarjinja/dirtree.py"}},"tarjinja_expand_py":{"hash":"04a9ab8a1772ca1ef386fce5a1af5db4","index":{"nums":[1,18,0,0,0,0,0],"html_filename":"tarjinja_expand_py.html","relative_filename":"tarjinja/expand.py"}},"tarjinja_git_py":{"hash":"9ecce216c7217c5f41187e14eafecee0","index":{"nums":[1,36,0,23,0,0,0],"html_filename":"tarjinja_git_py.html","relative_filename":"tarjinja/git.py"}},"tarjinja_iface_py":{"hash":"f1f4ea88c08087854456e1173f31ed4f","index":{"nums":[1,61,0,5,0,0,0],"html_filename":"tarjinja_iface_py.html","relative_filename":"tarjinja/iface.py"}},"tarjinja_jinjafilter_py":{"hash":"113fd1c0bfc95874ece8e2e3d9d76689","index":{"nums":[1,22,0,0,0,0,0],"html_filename":"tarjinja_jinjafilter_py.html","relative_filename":"tarjinja/jinjafilter.py"}},"tarjinja_makofilter_py":{"hash":"bd331f304f4c461a15a7108c86a8cdb3","index":{"nums":[1,5,0,1,0,0,0],"html_filename":"tarjinja_makofilter_py.html","relative_filename":"tarjinja/makofilter.py"}},"tarjinja_multifilter_py":{"hash":"a80d5fc00c4073b057e9732b16d38f59","index":{"nums":[1,10,0,0,0,0,0],"html_filename":"tarjinja_multifilter_py.html","relative_filename":"tarjinja/multifilter.py"}},"tarjinja_nullfilter_py":{"hash":"8e0bd697b540ee57f04458d2c52ffa54","index":{"nums":[1,9,0,3,0,0,0],"html_filename":"tarjinja_nullfilter_py.html","relative_filename":"tarjinja/nullfilter.py"}},"tarjinja_reversefilter_py":{"hash":"00f37becce0f69efff4fe428a18d143a","index":{"nums":[1,38,0,0,0,0,0],"html_filename":"tarjinja_reversefilter_py.html","relative_filename":"tarjinja/reversefilter.py"}},"tarjinja_strfilter_py":{"hash":"00da6308888162edc7cc39e1fa460a5e","index":{"nums":[1,30,0,0,0,0,0],"html_filename":"tarjinja_strfilter_py.html","relative_filename":"tarjinja/strfilter.py"}},"tarjinja_tar_py":{"hash":"5a30b516b612845599e32eafea163573","index":{"nums":[1,53,0,9,0,0,0],"html_filename":"tarjinja_tar_py.html","relative_filename":"tarjinja/tar.py"}},"tarjinja_version_py":{"hash":"2192e3ca52ab329b315670f6316667e4","index":{"nums":[1,1,0,0,0,0,0],"html_filename":"tarjinja_version_py.html","relative_filename":"tarjinja/version.py"}},"tarjinja_zip_py":{"hash":"f7565d5996cda84d2f12b8bd8cd1e06a","index":{"nums":[1,40,0,1,0,0,0],"html_filename":"tarjinja_zip_py.html","relative_filename":"tarjinja/zip.py"}}}}